verilator/__init__.py
verilator/__main__.py
verilator/cli.py
verilator/bin/verilator
verilator/bin/verilator_bin.exe
verilator/bin/verilator_includer
verilator/include/verilated.cpp
verilator/include/verilated.h
verilator/include/verilated.mk
verilator/include/verilated.v
verilator/include/verilated_config.h
verilator/include/verilated_cov.cpp
verilator/include/verilated_cov.h
verilator/include/verilated_cov_key.h
verilator/include/verilated_dpi.cpp
verilator/include/verilated_dpi.h
verilator/include/verilated_fst_c.cpp
verilator/include/verilated_fst_c.h
verilator/include/verilated_fst_sc.cpp
verilator/include/verilated_fst_sc.h
verilator/include/verilated_funcs.h
verilator/include/verilated_imp.h
verilator/include/verilated_intrinsics.h
verilator/include/verilated_probdist.cpp
verilator/include/verilated_profiler.cpp
verilator/include/verilated_profiler.h
verilator/include/verilated_random.cpp
verilator/include/verilated_random.h
verilator/include/verilated_saif_c.cpp
verilator/include/verilated_saif_c.h
verilator/include/verilated_saif_sc.h
verilator/include/verilated_save.cpp
verilator/include/verilated_save.h
verilator/include/verilated_sc.h
verilator/include/verilated_sc_trace.h
verilator/include/verilated_std.sv
verilator/include/verilated_std_waiver.vlt
verilator/include/verilated_sym_props.h
verilator/include/verilated_syms.h
verilator/include/verilated_threads.cpp
verilator/include/verilated_threads.h
verilator/include/verilated_timing.cpp
verilator/include/verilated_timing.h
verilator/include/verilated_trace.h
verilator/include/verilated_trace_imp.h
verilator/include/verilated_types.h
verilator/include/verilated_vcd_c.cpp
verilator/include/verilated_vcd_c.h
verilator/include/verilated_vcd_sc.cpp
verilator/include/verilated_vcd_sc.h
verilator/include/verilated_vpi.cpp
verilator/include/verilated_vpi.h
verilator/include/verilatedos.h
verilator/include/verilatedos_c.h
verilator/include/gtkwave/fastlz.c
verilator/include/gtkwave/fastlz.h
verilator-5.38.0.dist-info/METADATA
verilator-5.38.0.dist-info/WHEEL
verilator-5.38.0.dist-info/entry_points.txt
verilator-5.38.0.dist-info/licenses/LICENSE
verilator-5.38.0.dist-info/RECORD
