Metadata-Version: 2.4
Name: verilator
Version: 5.38.0
Summary: Python wrapping/binding for verilator
Project-URL: Repository, https://github.com/dau-dev/verilator-python
Project-URL: Homepage, https://github.com/dau-dev/verilator-python
Author-email: the verilator-python authors <dev@dau.dev>
License: Apache-2.0
License-File: LICENSE
Classifier: Development Status :: 3 - Alpha
Classifier: Programming Language :: Python
Classifier: Programming Language :: Python :: 3
Classifier: Programming Language :: Python :: 3.9
Classifier: Programming Language :: Python :: 3.10
Classifier: Programming Language :: Python :: 3.11
Classifier: Programming Language :: Python :: 3.12
Classifier: Programming Language :: Python :: 3.13
Requires-Python: >=3.9
Provides-Extra: cli
Requires-Dist: rich; extra == 'cli'
Requires-Dist: typer; extra == 'cli'
Provides-Extra: develop
Requires-Dist: build; extra == 'develop'
Requires-Dist: cibuildwheel; extra == 'develop'
Requires-Dist: hatchling; extra == 'develop'
Requires-Dist: pytest; extra == 'develop'
Requires-Dist: pytest-cov; extra == 'develop'
Requires-Dist: twine; extra == 'develop'
Requires-Dist: uv; extra == 'develop'
Requires-Dist: wheel; extra == 'develop'
